[{
	"model": "profile.profile",
	"pk": 1,
	"fields": {
		"password": "pbkdf2_sha256$36000$tXakM7GTgdMu$xP2xj6n+7sHBJ6jehamRGmsdvjRd6QB3wHhBQr9bE0k=",
		"last_login": "2017-06-09T23:23:09.667Z",
		"is_superuser": true,
		"username": "thingdeux",
		"first_name": "",
		"last_name": "",
		"is_staff": true,
		"is_active": true,
		"date_joined": "2017-06-09T23:22:14.332Z",
		"created": "2017-06-09T23:22:14.425Z",
		"last_modified": "2017-06-09T23:22:14.425Z",
		"email": "me@josh.land",
		"avatar_url": "http://static.goranked.com/ava1.jpg",
		"is_partner": false,
		"is_featured": false,
		"last_logged_in": "2017-06-09",
		"phone_number": null,
		"groups": [],
		"user_permissions": [],
		"followed_profiles": []
	}
}, {
	"model": "oauth2_provider.refreshtoken",
	"pk": 1,
	"fields": {
		"user": 1,
		"token": "Y5mYBxZkPfzalzyig9utB1EcH027IX",
		"application": 1,
		"access_token": 1
	}
}, {
	"model": "oauth2_provider.refreshtoken",
	"pk": 2,
	"fields": {
		"user": 1,
		"token": "XF5kHL1Qqv6DffMjFQR5cjJiYeJxhB",
		"application": 1,
		"access_token": 2
	}
}, {
	"model": "oauth2_provider.accesstoken",
	"pk": 1,
	"fields": {
		"user": 1,
		"token": "30UvWRQABc4zVcSuTUvHUgBPkNQ2Dc",
		"application": 1,
		"expires": "2017-06-10T09:42:16.745Z",
		"scope": "read write"
	}
}, {
	"model": "oauth2_provider.accesstoken",
	"pk": 2,
	"fields": {
		"user": 1,
		"token": "TC14TmaY69ZCWa0vSpvN5WKttHIEQE",
		"application": 1,
		"expires": "2018-06-10T09:47:37.928Z",
		"scope": "read write"
	}
}, {
	"model": "oauth2_provider.application",
	"pk": 1,
	"fields": {
		"client_id": "j7jhdBmo7jqw6CjZoBvgHK0FjZ0vzag8iypDs7x6",
		"user": 1,
		"redirect_uris": "",
		"client_type": "public",
		"authorization_grant_type": "password",
		"client_secret": "kRpxWpUeEFbhk1XL9KFv4wVDgcIag2OnuDdvyWuuqPSWOzRVlple4TqdCNDxdEfvwuoMOWoN0USoRUhJIl8gp3MrrY67njIV5BE29FOpOR07nihHNvS4PZR90KILTFIb",
		"name": "ranked",
		"skip_authorization": false
	}
}, {
	"model": "admin.logentry",
	"pk": 1,
	"fields": {
		"action_time": "2017-06-09T23:41:16.756Z",
		"user": 1,
		"content_type": 7,
		"object_id": "1",
		"object_repr": "ranked",
		"action_flag": 2,
		"change_message": "[{\"changed\": {\"fields\": [\"authorization_grant_type\"]}}]"
	}
}, {
	"model": "admin.logentry",
	"pk": 2,
	"fields": {
		"action_time": "2017-06-09T23:41:53.545Z",
		"user": 1,
		"content_type": 7,
		"object_id": "1",
		"object_repr": "ranked",
		"action_flag": 2,
		"change_message": "[{\"changed\": {\"fields\": [\"authorization_grant_type\"]}}]"
	}
}]